shellmarks.py
shellmarks-3.0.0.dist-info/LICENSE
shellmarks-3.0.0.dist-info/METADATA
shellmarks-3.0.0.dist-info/WHEEL
shellmarks-3.0.0.dist-info/RECORD
