Metadata-Version: 2.1
Name: shellmarks
Version: 3.0.0
Summary: shellmarks is a ansible module to set bookmarks to commonly used directories like the tools shellmarks and bashmarks do.
Home-page: https://github.com/Josef-Friedrich/ansible-module-shellmarks
License: GPL-3.0-only
Author: Josef Friedrich
Author-email: josef@friedrich.rocks
Requires-Python: >=3.10,<4.0
Classifier: License :: OSI Approved :: GNU General Public License v3 (GPLv3)
Classifier: Programming Language :: Python :: 3
Classifier: Programming Language :: Python :: 3.10
Classifier: Programming Language :: Python :: 3.11
Classifier: Programming Language :: Python :: 3.12
Classifier: Programming Language :: Python :: 3 :: Only
Requires-Dist: ansible (>=9,<10)
Project-URL: Repository, https://github.com/Josef-Friedrich/ansible-module-shellmarks
